dustysn/model.py
dustysn/plot.py
dustysn/utils.py
dustysn/ref_data/dust/k_Carbon.dat
dustysn/ref_data/dust/k_Silicate.dat
dustysn/ref_data/filters/JWST_MIRI_F1000W.txt
dustysn/ref_data/filters/JWST_MIRI_F1065C.txt
dustysn/ref_data/filters/JWST_MIRI_F1130W.txt
dustysn/ref_data/filters/JWST_MIRI_F1140C.txt
dustysn/ref_data/filters/JWST_MIRI_F1280W.txt
dustysn/ref_data/filters/JWST_MIRI_F1500W.txt
dustysn/ref_data/filters/JWST_MIRI_F1550C.txt
dustysn/ref_data/filters/JWST_MIRI_F1800W.txt
dustysn/ref_data/filters/JWST_MIRI_F2100W.txt
dustysn/ref_data/filters/JWST_MIRI_F2300C.txt
dustysn/ref_data/filters/JWST_MIRI_F2550W.txt
dustysn/ref_data/filters/JWST_MIRI_F560W.txt
dustysn/ref_data/filters/JWST_MIRI_F770W.txt
dustysn/ref_data/filters/JWST_NIRCAM_F115W.txt
dustysn/ref_data/filters/JWST_NIRCAM_F140M.txt
dustysn/ref_data/filters/JWST_NIRCAM_F150W.txt
dustysn/ref_data/filters/JWST_NIRCAM_F150W2.txt
dustysn/ref_data/filters/JWST_NIRCAM_F162M.txt
dustysn/ref_data/filters/JWST_NIRCAM_F164N.txt
dustysn/ref_data/filters/JWST_NIRCAM_F182M.txt
dustysn/ref_data/filters/JWST_NIRCAM_F187N.txt
dustysn/ref_data/filters/JWST_NIRCAM_F200W.txt
dustysn/ref_data/filters/JWST_NIRCAM_F210M.txt
dustysn/ref_data/filters/JWST_NIRCAM_F212N.txt
dustysn/ref_data/filters/JWST_NIRCAM_F250M.txt
dustysn/ref_data/filters/JWST_NIRCAM_F277W.txt
dustysn/ref_data/filters/JWST_NIRCAM_F300M.txt
dustysn/ref_data/filters/JWST_NIRCAM_F322W2.txt
dustysn/ref_data/filters/JWST_NIRCAM_F323N.txt
dustysn/ref_data/filters/JWST_NIRCAM_F335M.txt
dustysn/ref_data/filters/JWST_NIRCAM_F356W.txt
dustysn/ref_data/filters/JWST_NIRCAM_F360M.txt
dustysn/ref_data/filters/JWST_NIRCAM_F405N.txt
dustysn/ref_data/filters/JWST_NIRCAM_F410M.txt
dustysn/ref_data/filters/JWST_NIRCAM_F430M.txt
dustysn/ref_data/filters/JWST_NIRCAM_F444W.txt
dustysn/ref_data/filters/JWST_NIRCAM_F460M.txt
dustysn/ref_data/filters/JWST_NIRCAM_F466N.txt
dustysn/ref_data/filters/JWST_NIRCAM_F470N.txt
dustysn/ref_data/filters/JWST_NIRCAM_F480M.txt
dustysn-0.2.dist-info/METADATA
dustysn-0.2.dist-info/WHEEL
dustysn-0.2.dist-info/top_level.txt
dustysn-0.2.dist-info/RECORD
