Metadata-Version: 2.4
Name: dustysn
Version: 0.2
Summary: Package to fit the SEDs of dusty supernovae.
Home-page: https://github.com/gmzsebastian/dustysn
Author: Sebastian Gomez
Author-email: sebastian.gomez@austin.utexas.edu
License: MIT
Requires-Python: >=3.6
Requires-Dist: numpy
Requires-Dist: matplotlib
Requires-Dist: astropy
Requires-Dist: scipy
Requires-Dist: emcee
Dynamic: author
Dynamic: author-email
Dynamic: home-page
Dynamic: license
Dynamic: requires-dist
Dynamic: requires-python
Dynamic: summary
